fw_http_client/__init__.py
fw_http_client/client.py
fw_http_client/config.py
fw_http_client/errors.py
fw_http_client-1.7.5.dist-info/METADATA
fw_http_client-1.7.5.dist-info/WHEEL
fw_http_client-1.7.5.dist-info/licenses/LICENSE
fw_http_client-1.7.5.dist-info/RECORD
