Metadata-Version: 2.4
Name: fw-http-client
Version: 1.7.5
Summary: Prod-ready HTTP client with timeout and retries
Project-URL: Repository, https://gitlab.com/flywheel-io/tools/lib/fw-http-client
Project-URL: Documentation, https://gitlab.com/flywheel-io/tools/lib/fw-http-client
Author-email: Flywheel <support@flywheel.io>
License-Expression: MIT
License-File: LICENSE
Keywords: Flywheel,HTTP,client
Classifier: Topic :: Software Development :: Libraries :: Python Modules
Requires-Python: <4,>=3.9
Requires-Dist: fw-utils>=3
Requires-Dist: pydantic<3,>=2.1.1
Requires-Dist: requests<3,>=2.24.0
Requires-Dist: urllib3>=1.26.15
